litespeech/__init__.py
litespeech/client.py
litespeech/config.py
litespeech/exceptions.py
litespeech/version.py
litespeech/adapters/__init__.py
litespeech/adapters/anthropic_adapter.py
litespeech/adapters/auto_detect.py
litespeech/adapters/base.py
litespeech/adapters/litellm_adapter.py
litespeech/adapters/openai_adapter.py
litespeech/audio/__init__.py
litespeech/audio/conversion.py
litespeech/audio/detection.py
litespeech/audio/inspector.py
litespeech/audio/specs.py
litespeech/audio/stream_validator.py
litespeech/audio/streaming.py
litespeech/audio/types.py
litespeech/audio/validation.py
litespeech/providers/__init__.py
litespeech/providers/base.py
litespeech/providers/registry.py
litespeech/providers/asr/__init__.py
litespeech/providers/asr/azure.py
litespeech/providers/asr/cartesia.py
litespeech/providers/asr/deepgram.py
litespeech/providers/asr/elevenlabs.py
litespeech/providers/asr/openai.py
litespeech/providers/metadata/cartesia_asr.json
litespeech/providers/metadata/cartesia_tts.json
litespeech/providers/metadata/deepgram_asr.json
litespeech/providers/metadata/deepgram_tts.json
litespeech/providers/tts/__init__.py
litespeech/providers/tts/azure.py
litespeech/providers/tts/cartesia.py
litespeech/providers/tts/deepgram.py
litespeech/providers/tts/elevenlabs.py
litespeech/providers/tts/openai.py
litespeech/utils/__init__.py
litespeech/utils/debug.py
litespeech/utils/logging.py
litespeech-0.2.0.dist-info/METADATA
litespeech-0.2.0.dist-info/WHEEL
litespeech-0.2.0.dist-info/licenses/LICENSE
litespeech-0.2.0.dist-info/RECORD
