Metadata-Version: 2.4
Name: litespeech
Version: 0.2.0
Summary: Unified SDK for speech operations (ASR/TTS) with streaming support across multiple providers
Project-URL: Homepage, https://github.com/litespeech/litespeech
Project-URL: Documentation, https://github.com/litespeech/litespeech#readme
Project-URL: Repository, https://github.com/litespeech/litespeech
Project-URL: Issues, https://github.com/litespeech/litespeech/issues
Author-email: Sawradip Saha <sawradip0@gmail.com>
Maintainer-email: Sawradip Saha <sawradip0@gmail.com>
License: MIT
License-File: LICENSE
Keywords: asr,cartesia,deepgram,elevenlabs,speech,speech-to-text,streaming,text-to-speech,tts
Classifier: Development Status :: 3 - Alpha
Classifier: Intended Audience :: Developers
Classifier: License :: OSI Approved :: MIT License
Classifier: Programming Language :: Python :: 3
Classifier: Programming Language :: Python :: 3.9
Classifier: Programming Language :: Python :: 3.10
Classifier: Programming Language :: Python :: 3.11
Classifier: Programming Language :: Python :: 3.12
Classifier: Topic :: Multimedia :: Sound/Audio :: Speech
Classifier: Topic :: Scientific/Engineering :: Artificial Intelligence
Classifier: Typing :: Typed
Requires-Python: >=3.9
Requires-Dist: aiofiles>=24.1.0
Requires-Dist: httpx>=0.27.0
Requires-Dist: nest-asyncio>=1.5.0
Requires-Dist: pydantic>=2.0.0
Requires-Dist: websockets>=12.0
Provides-Extra: all
Requires-Dist: pydub>=0.25.0; extra == 'all'
Requires-Dist: soundfile>=0.12.0; extra == 'all'
Provides-Extra: audio
Requires-Dist: pydub>=0.25.0; extra == 'audio'
Requires-Dist: soundfile>=0.12.0; extra == 'audio'
Provides-Extra: dev
Requires-Dist: mypy>=1.8.0; extra == 'dev'
Requires-Dist: pytest-asyncio>=0.23.0; extra == 'dev'
Requires-Dist: pytest-cov>=4.0.0; extra == 'dev'
Requires-Dist: pytest>=8.0.0; extra == 'dev'
Requires-Dist: ruff>=0.3.0; extra == 'dev'
